twitch/__init__.py
twitch/client.py
twitch/exception.py
twitch/models.py
twitch/params.py
py_twitch-0.1.3.dist-info/METADATA
py_twitch-0.1.3.dist-info/WHEEL
py_twitch-0.1.3.dist-info/top_level.txt
py_twitch-0.1.3.dist-info/RECORD
