Metadata-Version: 2.1
Name: py-twitch
Version: 0.1.3
Summary: Twitch API Python client
Home-page: https://github.com/helloracoon/py-twitch
Author: TEMP USER
Author-email: useradd.temp@gmail.com
License: UNKNOWN
Platform: UNKNOWN
Requires-Dist: dacite (==1.6.0)
Requires-Dist: requests (==2.25.1)
